swh/loader/mercurial/__init__.py
swh/loader/mercurial/archive_extract.py
swh/loader/mercurial/converters.py
swh/loader/mercurial/directory.py
swh/loader/mercurial/hgutil.py
swh/loader/mercurial/identify.py
swh/loader/mercurial/loader.py
swh/loader/mercurial/py.typed
swh/loader/mercurial/tasks.py
swh/loader/mercurial/utils.py
swh/loader/mercurial/tests/__init__.py
swh/loader/mercurial/tests/conftest.py
swh/loader/mercurial/tests/loader_checker.py
swh/loader/mercurial/tests/test_converters.py
swh/loader/mercurial/tests/test_directory.py
swh/loader/mercurial/tests/test_identify.py
swh/loader/mercurial/tests/test_loader.py
swh/loader/mercurial/tests/test_tasks.py
swh/loader/mercurial/tests/test_tasks_directory.py
swh/loader/mercurial/tests/data/anomad-d.tgz
swh/loader/mercurial/tests/data/build.py
swh/loader/mercurial/tests/data/example.json
swh/loader/mercurial/tests/data/example.sh
swh/loader/mercurial/tests/data/example.tgz
swh/loader/mercurial/tests/data/hello.json
swh/loader/mercurial/tests/data/hello.tgz
swh/loader/mercurial/tests/data/missing-filelog.sh
swh/loader/mercurial/tests/data/missing-filelog.tgz
swh/loader/mercurial/tests/data/multiple-heads.json
swh/loader/mercurial/tests/data/multiple-heads.sh
swh/loader/mercurial/tests/data/multiple-heads.tgz
swh/loader/mercurial/tests/data/the-sandbox.json
swh/loader/mercurial/tests/data/the-sandbox.tgz
swh/loader/mercurial/tests/data/transplant.json
swh/loader/mercurial/tests/data/transplant.tgz
swh_loader_mercurial-3.6.2.dist-info/licenses/AUTHORS
swh_loader_mercurial-3.6.2.dist-info/licenses/LICENSE
swh_loader_mercurial-3.6.2.dist-info/METADATA
swh_loader_mercurial-3.6.2.dist-info/WHEEL
swh_loader_mercurial-3.6.2.dist-info/entry_points.txt
swh_loader_mercurial-3.6.2.dist-info/top_level.txt
swh_loader_mercurial-3.6.2.dist-info/RECORD
